LICENSE.txt
MANIFEST.in
README.md
requirements-dev.txt
requirements-test.txt
setup.py
humilis_batch/__init__.py
humilis_batch/meta.yaml.j2
humilis_batch/outputs.yaml.j2
humilis_batch/plugin.py
humilis_batch/resources.yaml.j2
humilis_batch.egg-info/PKG-INFO
humilis_batch.egg-info/SOURCES.txt
humilis_batch.egg-info/dependency_links.txt
humilis_batch.egg-info/entry_points.txt
humilis_batch.egg-info/not-zip-safe
humilis_batch.egg-info/requires.txt
humilis_batch.egg-info/top_level.txt