Metadata-Version: 1.1
Name: humilis-batch
Version: 0.1.3
Summary: Humilis plug-in to deploy AWS Batch resources
Home-page: https://github.com/humilis/humilis-batch
Author: German Gomez-Herrero
Author-email: german@findhotel.net
License: MIT
Platform: UNKNOWN
Classifier: Programming Language :: Python :: 3
